fwl_mors-26.1.2.dist-info/licenses/LICENSE.md
mors/__init__.py
mors/baraffe.py
mors/cli.py
mors/cluster.py
mors/constants.py
mors/data.py
mors/logs.py
mors/miscellaneous.py
mors/parameters.py
mors/physicalmodel.py
mors/rotevo.py
mors/spectrum.py
mors/star.py
mors/stellarevo.py
mors/synthesis.py
mors/data/ModelDistribution.dat
fwl_mors-26.1.2.dist-info/METADATA
fwl_mors-26.1.2.dist-info/WHEEL
fwl_mors-26.1.2.dist-info/entry_points.txt
fwl_mors-26.1.2.dist-info/top_level.txt
fwl_mors-26.1.2.dist-info/RECORD
