Metadata-Version: 2.4
Name: fwl-mors
Version: 26.1.2
Summary: Stellar rotation and activity evolution model
Author-email: "Colin P. Johnstone" <colinjohnstone@gmail.com>, Harrison Nicholls <harrison.nicholls@physics.ox.ac.uk>, Laurent Soucasse <l.soucasse@esciencecenter.nl>
License: MIT License
Project-URL: homepage, https://github.com/FormingWorlds/MORS
Keywords: exoplanet,stellar evolution
Classifier: Intended Audience :: Science/Research
Classifier: License :: OSI Approved :: MIT License
Classifier: Natural Language :: English
Classifier: Operating System :: OS Independent
Classifier: Programming Language :: Python
Classifier: Programming Language :: Python :: 3.11
Classifier: Programming Language :: Python :: 3.12
Classifier: Programming Language :: Python :: 3.13
Requires-Python: >=3.11
License-File: LICENSE.md
Requires-Dist: click
Requires-Dist: matplotlib
Requires-Dist: numpy>=2.0.0
Requires-Dist: osfclient
Requires-Dist: platformdirs
Requires-Dist: scipy
Requires-Dist: zenodo_get
Provides-Extra: develop
Requires-Dist: bump-my-version; extra == "develop"
Requires-Dist: coverage[toml]; extra == "develop"
Requires-Dist: pip-tools; extra == "develop"
Requires-Dist: pytest; extra == "develop"
Provides-Extra: docs
Requires-Dist: markdown-include; extra == "docs"
Requires-Dist: mkdocs; extra == "docs"
Requires-Dist: mkdocs-material; extra == "docs"
Requires-Dist: mkdocstrings[python]; extra == "docs"
Provides-Extra: publishing
Requires-Dist: twine; extra == "publishing"
Requires-Dist: wheel; extra == "publishing"
Requires-Dist: build; extra == "publishing"
Dynamic: license-file
